<?xml version="1.0" encoding="UTF-8"?><record_update>
    <sys_ui_form_sections action="DELETE" form_id="868da114c3d27d10c00c753ce0013183" sys_domain="global" table="x_58872_needit_needit" version="3">
        <sys_ui_form action="INSERT_OR_UPDATE">
            <name>x_58872_needit_needit</name>
            <roles/>
            <sys_class_name>sys_ui_form</sys_class_name>
            <sys_created_by>admin</sys_created_by>
            <sys_created_on>2023-10-31 07:14:50</sys_created_on>
            <sys_domain>global</sys_domain>
            <sys_domain_path>/</sys_domain_path>
            <sys_id>868da114c3d27d10c00c753ce0013183</sys_id>
            <sys_mod_count>0</sys_mod_count>
            <sys_name>x_58872_needit_needit</sys_name>
            <sys_overrides/>
            <sys_package display_value="NeedIt" source="x_58872_needit">6ead8e780f603200cd674f8ce1050ed1</sys_package>
            <sys_policy/>
            <sys_scope display_value="NeedIt">6ead8e780f603200cd674f8ce1050ed1</sys_scope>
            <sys_update_name>sys_ui_form_sections_868da114c3d27d10c00c753ce0013183</sys_update_name>
            <sys_updated_by>admin</sys_updated_by>
            <sys_updated_on>2023-10-31 07:14:50</sys_updated_on>
            <sys_user/>
            <view display_value="">5bd975bd0fa03200cd674f8ce1050e7f</view>
            <view_name/>
        </sys_ui_form>
    </sys_ui_form_sections>
    <sys_update_version action="INSERT_OR_UPDATE">
        <action>DELETE</action>
        <application display_value="NeedIt">6ead8e780f603200cd674f8ce1050ed1</application>
        <file_path/>
        <instance_id>4dde4563db1989101b813feb68961906</instance_id>
        <instance_name>dev124148</instance_name>
        <name>sys_ui_form_sections_868da114c3d27d10c00c753ce0013183</name>
        <payload><![CDATA[<?xml version="1.0" encoding="UTF-8"?><record_update><sys_ui_form_sections form_id="868da114c3d27d10c00c753ce0013183" sys_domain="global" table="x_58872_needit_needit" version="3"><sys_ui_form action="INSERT_OR_UPDATE"><name>x_58872_needit_needit</name><roles/><sys_class_name>sys_ui_form</sys_class_name><sys_created_by>admin</sys_created_by><sys_created_on>2023-10-31 07:14:50</sys_created_on><sys_domain>global</sys_domain><sys_domain_path>/</sys_domain_path><sys_id>868da114c3d27d10c00c753ce0013183</sys_id><sys_mod_count>0</sys_mod_count><sys_name>x_58872_needit_needit</sys_name><sys_overrides/><sys_package display_value="NeedIt" source="x_58872_needit">6ead8e780f603200cd674f8ce1050ed1</sys_package><sys_policy/><sys_scope display_value="NeedIt">6ead8e780f603200cd674f8ce1050ed1</sys_scope><sys_update_name>sys_ui_form_sections_868da114c3d27d10c00c753ce0013183</sys_update_name><sys_updated_by>admin</sys_updated_by><sys_updated_on>2023-10-31 07:14:50</sys_updated_on><sys_user/><view display_value="">5bd975bd0fa03200cd674f8ce1050e7f</view><view_name/></sys_ui_form></sys_ui_form_sections></record_update>]]></payload>
        <payload_hash>984810782</payload_hash>
        <record_name>NeedIt</record_name>
        <reverted_from/>
        <source>a22aca13c38a7910c00c753ce00131ce</source>
        <source_table>sys_update_set</source_table>
        <state>previous</state>
        <sys_created_by>admin</sys_created_by>
        <sys_created_on>2023-10-31 10:44:15</sys_created_on>
        <sys_id>397d5a50c3967d10c00c753ce0013197</sys_id>
        <sys_mod_count>0</sys_mod_count>
        <sys_recorded_at>18b8555836e0000001</sys_recorded_at>
        <sys_updated_by>admin</sys_updated_by>
        <sys_updated_on>2023-10-31 10:44:15</sys_updated_on>
        <type>Form Sections</type>
        <update_guid>fd7d5a50aa967d10611837260c01c796</update_guid>
        <update_guid_history>fd7d5a50aa967d10611837260c01c796:984810782,18171ad890567d10c97bb20e80af0271:-122411134,94171ad8c7567d1093938baf1e5c8568:-876626380,58171ad838567d103db747fc567a5551:-529150627,ce8da1148ad27d1084852932f6c2f598:837569133,468da114c7d27d105b42baac32472495:1721131195,868da1144ed27d10c1c32aa403d3f585:-122411134</update_guid_history>
    </sys_update_version>
    <sys_metadata_delete action="INSERT_OR_UPDATE">
        <sys_audit_delete/>
        <sys_class_name>sys_metadata_delete</sys_class_name>
        <sys_created_by>admin</sys_created_by>
        <sys_created_on>2023-10-31 10:44:15</sys_created_on>
        <sys_db_object display_value="" name="sys_ui_form">sys_ui_form</sys_db_object>
        <sys_id>58ef8604a66447048c0cd497c13f5d10</sys_id>
        <sys_metadata>868da114c3d27d10c00c753ce0013183</sys_metadata>
        <sys_mod_count>0</sys_mod_count>
        <sys_name>x_58872_needit_needit</sys_name>
        <sys_package display_value="NeedIt" source="x_58872_needit">6ead8e780f603200cd674f8ce1050ed1</sys_package>
        <sys_parent display_value="NeedIt">0aa543dfc34e7910c00c753ce001315a</sys_parent>
        <sys_policy/>
        <sys_scope display_value="NeedIt">6ead8e780f603200cd674f8ce1050ed1</sys_scope>
        <sys_scope_delete display_value="">94872a8897db403e8ee69a431de2fca4</sys_scope_delete>
        <sys_update_name>sys_ui_form_sections_868da114c3d27d10c00c753ce0013183</sys_update_name>
        <sys_update_version display_value="sys_ui_form_sections_868da114c3d27d10c00c753ce0013183">397d5a50c3967d10c00c753ce0013197</sys_update_version>
        <sys_updated_by>admin</sys_updated_by>
        <sys_updated_on>2023-10-31 10:44:15</sys_updated_on>
    </sys_metadata_delete>
</record_update>
